{
  "type": "FeatureCollection",
  "features": [
    {
      "type": "Feature",
      "properties": {
        "city": "巴黎",
        "name": "Hotel-Dieu de Paris"
      },
      "geometry": {
        "type": "Point",
        "coordinates": [
          2.3492,
          48.8549
        ]
      }
    }
  ]
}